[{"id":1,"book":1,"format":"EPUB","uncompressed_size":1048980,"name":"Viet Nam Phat giao su luan - Nguyen Lang"},{"id":2,"book":3,"format":"PDF","uncompressed_size":2376257,"name":"Su-Song-That-Trong-Thien-Chua-5 - Vassula Ryden"},{"id":3,"book":4,"format":"PDF","uncompressed_size":3507550,"name":"Su-Song-That-Trong-Thien-Chua-1 - Vassula Ryden"},{"id":4,"book":5,"format":"PDF","uncompressed_size":2531242,"name":"Su Song That Trong Thien Chua 6 - Vassula Ryden"},{"id":5,"book":6,"format":"PDF","uncompressed_size":3775515,"name":"Su-Song-That-Trong-Thien-Chua-2 - Vassula Ryden"},{"id":6,"book":7,"format":"PDF","uncompressed_size":3702225,"name":"Su-Song-That-Trong-Thien-Chua-3 - Vassula Ryden"},{"id":7,"book":8,"format":"PDF","uncompressed_size":3298171,"name":"Su-Song-That-Trong-Thien-Chua-4 - Vassula Ryden"},{"id":8,"book":9,"format":"PRC","uncompressed_size":195684,"name":"Thien Quan - Tieng Chuong Vuot - U Ba Khin"},{"id":9,"book":10,"format":"PDF","uncompressed_size":3399885,"name":"Su thay doi cua trai dat va nam - Sal Rachele"},{"id":10,"book":11,"format":"PDF","uncompressed_size":973310,"name":"Su thay doi cua trai dat va nam - Sal Rachele"},{"id":11,"book":12,"format":"PDF","uncompressed_size":2790019,"name":"Hoang De noi kinh to van (toan - THIEN LANG"},{"id":12,"book":13,"format":"EPUB","uncompressed_size":1183896,"name":"Chuyen Phap Luan - Su phu Ly Hong Chi"},{"id":13,"book":14,"format":"EPUB","uncompressed_size":1202739,"name":"Kinh Nikaya II - Trung Bo Kinh - Thich Minh Chau dich"},{"id":14,"book":15,"format":"EPUB","uncompressed_size":848899,"name":"Kinh Nikaya I - Truong Bo Kinh - Thich Minh Chau dich"},{"id":15,"book":16,"format":"EPUB","uncompressed_size":818473,"name":"Kinh Nikaya IV - Tang Chi Bo Ki - Thich Minh Chau dich"},{"id":16,"book":17,"format":"EPUB","uncompressed_size":1348523,"name":"Kinh Nikaya III - Tuong Ung Bo - Thich Minh Chau dich"},{"id":17,"book":18,"format":"EPUB","uncompressed_size":2575214,"name":"Kinh Nikaya V - Tieu Bo Kinh - Thich Minh Chau dich"},{"id":18,"book":19,"format":"PDF","uncompressed_size":3575709,"name":"Hoang De Noi Kinh Quyen 2 - Chon Nguyen"},{"id":19,"book":20,"format":"PDF","uncompressed_size":8965550,"name":"Hoang De Noi Kinh Quyen 1 - Chon Nguyen"},{"id":20,"book":21,"format":"PDF","uncompressed_size":2790019,"name":"B - THIEN LANG"},{"id":21,"book":22,"format":"PDF","uncompressed_size":519596,"name":"LIEU PHAM TU HUAN - An Quang Dai Su"},{"id":22,"book":23,"format":"PRC","uncompressed_size":390036,"name":"1 Harry Potter va Hon Da Phu Th - J.K.Rowling"},{"id":23,"book":24,"format":"PRC","uncompressed_size":526008,"name":"7 Harry Potter and the Deathly - J.K.Rowling"},{"id":24,"book":25,"format":"PRC","uncompressed_size":761752,"name":"6 Harry Potter va Hoang Tu Lai - J.K.Rowling"},{"id":25,"book":26,"format":"PRC","uncompressed_size":1245128,"name":"5 Harry Potter va Mat Lenh Phuo - J.K.Rowling"},{"id":26,"book":27,"format":"PRC","uncompressed_size":994000,"name":"4 Harry Potter va Chiec Coc Lua - J.K.Rowling"},{"id":27,"book":28,"format":"PRC","uncompressed_size":588928,"name":"3 Harry Potter va Ten Tu Nhan N - J.K.Rowling"},{"id":28,"book":29,"format":"PRC","uncompressed_size":461832,"name":"2 Harry Potter va Phong Chua Bi - J.K.Rowling"},{"id":30,"book":32,"format":"EPUB","uncompressed_size":1725722,"name":"Tieu ngao giang ho - Kim Dung"}]